[{"Id":6,"StreetName":"nja","HouseNumber":121,"Adults":[],"Children":[{"ChildInterests":[{"Type":"Kite Flying","validTypes":["Soccer","Drawing","Kite Flying","Roller Blades","Board Games","Ballet","Hockey","Gaming","Lego","Scout","Gymnastics","Harry Potter","Frozen"]},{"Type":"Drawing","validTypes":["Soccer","Drawing","Kite Flying","Roller Blades","Board Games","Ballet","Hockey","Gaming","Lego","Scout","Gymnastics","Harry Potter","Frozen"]}],"Pets":[{"Id":1,"Species":"Hamster","Name":"1","Age":0}],"Id":6,"FirstName":null,"LastName":null,"HairColor":"Blond","EyeColor":"Black","Age":0,"Weight":11,"Height":122,"Sex":"Male"}],"Pets":[]},{"Id":7,"StreetName":"Njs","HouseNumber":121,"Adults":[],"Children":[{"ChildInterests":[{"Type":"Kite Flying","validTypes":["Soccer","Drawing","Kite Flying","Roller Blades","Board Games","Ballet","Hockey","Gaming","Lego","Scout","Gymnastics","Harry Potter","Frozen"]},{"Type":"Drawing","validTypes":["Soccer","Drawing","Kite Flying","Roller Blades","Board Games","Ballet","Hockey","Gaming","Lego","Scout","Gymnastics","Harry Potter","Frozen"]}],"Pets":[{"Id":1,"Species":"Hamster","Name":"1","Age":0}],"Id":6,"FirstName":null,"LastName":null,"HairColor":"Blond","EyeColor":"Black","Age":0,"Weight":11,"Height":122,"Sex":"Male"}],"Pets":[{"Id":0,"Species":"Snake","Name":"we","Age":1}]}]